mtx/Act.py
mtx/BaseObject.py
mtx/Cell.py
mtx/Constants.py
mtx/Field.py
mtx/Game.py
mtx/GameConsole.py
mtx/GameLoader.py
mtx/Level.py
mtx/Renderer.py
mtx/Settings.py
mtx/Utils.py
mtx/__init__.py
mtx/baseObjects/CollectableObject.py
mtx/baseObjects/MovableObject.py
mtx/baseObjects/RemovableObject.py
mtx/baseObjects/SolidObject.py
mtx/baseObjects/TriggerObject.py
mtx/baseObjects/__init__.py
mtx/objects/Box.py
mtx/objects/Cursor.py
mtx/objects/Dot.py
mtx/objects/Empty.py
mtx/objects/Exit.py
mtx/objects/Key.py
mtx/objects/Player.py
mtx/objects/Target.py
mtx/objects/Tile.py
mtx/objects/Wall.py
mtx/objects/__init__.py
mtxNet/ControllerHandler.py
mtxNet/ControllerServer.py
mtxNet/RendererClient.py
mtxNet/__init__.py
mtxNet/controllerService/ControllerService.py
mtxNet/controllerService/__init__.py
mtxNet/controllerService/constants.py
mtxNet/controllerService/ttypes.py
mtxNet/rendererService/RendererService.py
mtxNet/rendererService/__init__.py
mtxNet/rendererService/constants.py
mtxNet/rendererService/ttypes.py
mtxPython-0.1.0.dev11.dist-info/DESCRIPTION.rst
mtxPython-0.1.0.dev11.dist-info/METADATA
mtxPython-0.1.0.dev11.dist-info/RECORD
mtxPython-0.1.0.dev11.dist-info/WHEEL
mtxPython-0.1.0.dev11.dist-info/metadata.json
mtxPython-0.1.0.dev11.dist-info/top_level.txt
