Metadata-Version: 2.0
Name: mtxPython
Version: 0.1.0.dev11
Summary: A framework to create matrix games
Home-page: http://www.matrixgames.rocks
Author: Matrix Games Community
Author-email: info@matrixgames.rocks
License: GNU General Public License v3 (GPLv3)
Keywords: game,fun,framework
Platform: UNKNOWN
Classifier: Development Status :: 2 - Pre-Alpha
Classifier: Intended Audience :: Developers
Classifier: Topic :: Games/Entertainment
Classifier: License :: OSI Approved :: GNU General Public License v3 (GPLv3)
Classifier: Operating System :: OS Independent
Classifier: Programming Language :: Python :: 3
Classifier: Programming Language :: Python :: 3.3
Classifier: Programming Language :: Python :: 3.4
Classifier: Programming Language :: Python :: 3.5
Classifier: Natural Language :: English
